{
  "Purpose": "To track the source revision and build requirements of Visual Studio Plugins used by PluginRegistry",
  "Version": "1.0",
  "Plugins": {
    "atlassian.atlascode": {
      "repository": "https://bitbucket.org/atlassianlabs/atlascode",
      "revision": "3.0.6",
      "update": "true",
      "packageManager": "yarn@1.22.19"
    },
    "bmewburn.vscode-intelephense-client": {
      "repository": "https://github.com/bmewburn/vscode-intelephense",
      "revision": "v1.9.5",
      "update": "true"
    },
    "dbaeumer.vscode-eslint": {
      "repository": "https://github.com/microsoft/vscode-eslint",
      "revision": "release/2.4.2",
      "update": "true"
    },
    "donjayamanne.githistory": {
      "repository": "https://github.com/DonJayamanne/gitHistoryVSCode",
      "revision": "v0.6.20",
      "update": "true"
    },
    "eamodio.gitlens": {
      "repository": "https://github.com/gitkraken/vscode-gitlens",
      "revision": "v14.3.0",
      "update": "true",
      "ubi8Image": "nodejs-16:1-90",
      "packageManager": "yarn@1.22.10"
    },
    "eclipse-cdt.cdt-gdb-vscode": {
      "repository": "https://github.com/eclipse-cdt-cloud/cdt-gdb-vscode",
      "revision": "v0.0.102",
      "update": "true",
      "packageManager": "yarn@1.22.10"
    },
    "esbenp.prettier-vscode": {
      "repository": "https://github.com/prettier/prettier-vscode",
      "revision": "v10.1.0",
      "update": "true",
      "packageManager": "yarn@1.22.10"
    },
    "felixfbecker.php-debug": {
      "repository": "https://github.com/xdebug/vscode-php-debug",
      "revision": "v1.32.1",
      "update": "true",
      "ubi8Image": "nodejs-16:1-90"
    },
    "github.vscode-pull-request-github": {
      "repository": "https://github.com/microsoft/vscode-pull-request-github",
      "revision": "v0.72.0",
      "update": "true",
      "packageManager": "yarn@1.22.10"
    },
    "gitlab.gitlab-workflow": {
      "repository": "https://gitlab.com/gitlab-org/gitlab-vscode-extension.git/",
      "revision": "v3.77.1",
      "update": "true"
    },
    "golang.go": {
      "repository": "https://github.com/golang/vscode-go",
      "revision": "v0.39.1",
      "update": "true"
    },
    "jfrog.jfrog-vscode-extension": {
      "repository": "https://github.com/jfrog/jfrog-vscode-extension",
      "revision": "v2.7.1",
      "update": "true"
    },
    "llvm-vs-code-extensions.vscode-clangd": {
      "repository": "https://github.com/clangd/vscode-clangd",
      "revision": "0.1.24",
      "update": "true"
    },
    "ms-kubernetes-tools.vscode-kubernetes-tools": {
      "repository": "https://github.com/vscode-kubernetes-tools/vscode-kubernetes-tools",
      "revision": "1.3.13",
      "update": "true"
    },
    "ms-python.isort": {
      "repository": "https://github.com/microsoft/vscode-isort",
      "revision": "2023.10.1",
      "update": "true"
    },
    "ms-python.black-formatter": {
      "comment": "Version: 2023.4.1",
      "repository": "https://github.com/microsoft/vscode-black-formatter",
      "revision": "5f9153162a7b4e6b20d860474d3e61010a009785",
      "update": "true"
    },
    "ms-python.python": {
      "repository": "https://github.com/microsoft/vscode-python",
      "revision": "v2023.16.0",
      "update": "true"
    },
    "ms-toolsai.jupyter": {
      "comment": "Cannot be built due to https://github.com/microsoft/vscode-jupyter/issues/13260, tracked in https://issues.redhat.com/browse/CRW-4325",
      "repository": "https://github.com/microsoft/vscode-jupyter",
      "revision": "4733a075e8af70d358dba81987395c9150fe5802",
      "update": "false",
      "ubi8Image": "nodejs-16:1-90",
      "packageManager": "npm@6.14.18"
    },
    "ms-toolsai.jupyter-keymap": {
      "comment": "Version: 1.1.2",
      "repository": "https://github.com/microsoft/vscode-jupyter-keymap",
      "revision": "d2c7c446c92c35eebe67c702f017e555a61b1a6c",
      "update": "true"
    },
    "ms-toolsai.jupyter-renderers": {
      "comment": "Version: 1.0.17",
      "repository": "https://github.com/microsoft/vscode-notebook-renderers",
      "revision": "878a3ab392e04eb8cbdfd20ebd58d609067d00c1",
      "update": "true",
      "ubi8Image": "nodejs-16:1-90",
      "packageManager": "npm@8.15.1"
    },
    "ms-toolsai.vscode-jupyter-cell-tags": {
      "comment": "Version: 0.1.8",
      "repository": "https://github.com/Microsoft/vscode-jupyter-cell-tags",
      "revision": "5d4f72e96414442cf3afd91d8adb8fa6807fd778",
      "update": "true"
    },
    "ms-toolsai.vscode-jupyter-slideshow": {
      "comment": "Version: 0.1.5",
      "repository": "https://github.com/Microsoft/vscode-jupyter-slideshow",
      "revision": "2cf41f6d1f8c8045a6810ce922378ce731aac806",
      "update": "true"
    },
    "ms-vscode.js-debug": {
      "comment": "Needed for the devspaces-code build. Version must be kept in sync with  https://github.com/microsoft/vscode/blob/main/product.json#L35",
      "repository": "https://github.com/microsoft/vscode-js-debug",
      "revision": "v1.82.0",
      "update": "false"
    },
    "ms-vscode.js-debug-companion": {
      "comment": "Needed for the devspaces-code build. Version must be kept in sync with  https://github.com/microsoft/vscode/blob/main/product.json#L35",
      "repository": "https://github.com/microsoft/vscode-js-debug-companion",
      "revision": "v1.1.2",
      "update": "false"
    },
    "ms-vscode.vscode-js-profile-table": {
      "comment": "Needed for the devspaces-code build. Version must be kept in sync with  https://github.com/microsoft/vscode/blob/main/product.json#L35",
      "repository": "https://github.com/microsoft/vscode-js-profile-visualizer",
      "revision": "v1.0.3",
      "update": "false"
    },
    "ms-dotnettools.vscode-dotnet-runtime": {
      "repository": "https://github.com/dotnet/vscode-dotnet-runtime",
      "revision": "Runtime-v1.7.2",
      "packageManager": "yarn@1.22.10",
      "update": "false"
    },
    "muhammad-sammy.csharp": {
      "repository": "https://github.com/muhammadsammy/free-omnisharp-vscode",
      "revision": "2.0.436",
      "update": "true"
    },
    "redhat.ansible": {
      "repository": "https://github.com/ansible/vscode-ansible",
      "revision": "v2.4",
      "update": "false",
      "packageManager": "yarn@1.22.10"
    },
    "redhat.fabric8-analytics": {
      "repository": "https://github.com/fabric8-analytics/fabric8-analytics-vscode-extension",
      "revision": "0.7.0",
      "update": "true",
      "packageManager": "npm@6.14.17"
    },
    "redhat.java": {
      "repository": "https://github.com/redhat-developer/vscode-java",
      "revision": "v1.22.1",
      "update": "true",
      "ubi8Image": "nodejs-14:1-101",
      "packageManager": "npm@6.14.17"
    },
    "redhat.vscode-commons": {
      "comment": "Version: 0.0.6",
      "repository": "https://github.com/redhat-developer/vscode-commons",
      "revision": "021b0165bb5ba05e107ee7e31d1e59a7a73f473c",
      "update": "true"
    },
    "redhat.vscode-microprofile": {
      "repository": "https://github.com/redhat-developer/vscode-microprofile",
      "revision": "0.9.0",
      "update": "true"
    },
    "redhat.vscode-openshift-connector": {
      "repository": "https://github.com/redhat-developer/vscode-openshift-tools",
      "revision": "v1.8.0",
      "update": "true"
    },
    "redhat.vscode-quarkus": {
      "repository": "https://github.com/redhat-developer/vscode-quarkus",
      "revision": "v1.15.0",
      "update": "true",
      "ubi8Image": "nodejs-14:1-101",
      "packageManager": "npm@6.14.17"
    },
    "redhat.vscode-redhat-account": {
      "comment": "Version: 0.1.0",
      "repository": "https://github.com/redhat-developer/vscode-redhat-account",
      "revision": "b1e57fae4120291427bfea9685c4b069a2235405",
      "update": "true"
    },
    "redhat.vscode-tekton-pipelines": {
      "comment": "Setting to latest commit as of 06/26/2023 because previous released version no longer builds.",
      "repository": "https://github.com/redhat-developer/vscode-tekton",
      "revision": "97afeb1887774a3c1eccf3fd8a5ebea1ed53ee3a",
      "update": "false"
    },
    "redhat.vscode-xml": {
      "repository": "https://github.com/redhat-developer/vscode-xml",
      "revision": "0.26.1",
      "update": "true"
    },
    "redhat.vscode-yaml": {
      "repository": "https://github.com/redhat-developer/vscode-yaml",
      "revision": "1.14.0",
      "update": "true",
      "packageManager": "yarn@1.22.10"
    },
    "sonarsource.sonarlint-vscode": {
      "repository": "https://github.com/SonarSource/sonarlint-vscode",
      "revision": "3.19.2+73908",
      "update": "false"
    },
    "sonatypecommunity.vscode-iq-plugin": {
      "repository": "https://github.com/sonatype-nexus-community/vscode-iq-plugin",
      "revision": "v1.3.4",
      "update": "true"
    },
    "timonwong.shellcheck": {
      "repository": "https://github.com/vscode-shellcheck/vscode-shellcheck",
      "revision": "v0.34.0",
      "update": "true"
    },
    "vscjava.vscode-java-debug": {
      "repository": "https://github.com/microsoft/vscode-java-debug",
      "revision": "0.54.0",
      "update": "true"
    },
    "vscjava.vscode-java-test": {
      "repository": "https://github.com/microsoft/vscode-java-test",
      "revision": "0.39.1",
      "update": "true"
    },
    "xdebug.php-debug": {
      "repository": "https://github.com/xdebug/vscode-php-debug",
      "revision": "v1.33.0",
      "update": "true"
    }
  }
}
